chetoolbox/__init__.py
chetoolbox/common.py
chetoolbox/props.py
chetoolbox/separations.py
chetoolbox/transport.py
chetoolbox-0.0.11.dist-info/LICENSE.txt
chetoolbox-0.0.11.dist-info/METADATA
chetoolbox-0.0.11.dist-info/WHEEL
chetoolbox-0.0.11.dist-info/top_level.txt
chetoolbox-0.0.11.dist-info/RECORD
