Metadata-Version: 2.1
Name: chetoolbox
Version: 0.0.11
Summary: A library of common chemical engineering calculations
Author: Quan Phan & Ethan Molnar
Author-email: Phanqv@mail.uc.edu
Keywords: python,chemical engineering
Classifier: Development Status :: 3 - Alpha
Classifier: Intended Audience :: Education
Classifier: Programming Language :: Python :: 2
Classifier: Programming Language :: Python :: 3
Classifier: Operating System :: Microsoft :: Windows
License-File: LICENSE.txt
Requires-Dist: numpy
Requires-Dist: scipy
Requires-Dist: pandas
